knorket_router/__init__.py
knorket_router/cli.py
knorket_router/main.py
knorket_router-0.1.0.dist-info/METADATA
knorket_router-0.1.0.dist-info/WHEEL
knorket_router-0.1.0.dist-info/entry_points.txt
knorket_router-0.1.0.dist-info/top_level.txt
knorket_router-0.1.0.dist-info/RECORD
