Metadata-Version: 2.1
Name: knorket_router
Version: 0.1.0
Summary: A description of your package
Home-page: 
Author: sadath
Author-email: sadathsadu2002@gmail.com
Classifier: Programming Language :: Python :: 3
Classifier: License :: OSI Approved :: MIT License
Classifier: Operating System :: OS Independent
Requires-Python: >=3.6
